Labs/Lab_2/ALU.v
module ALU # ( parameter width = 8) (
  input wire [width - 1: 0] a,
  input wire [width - 1: 0] b,
  input wire [2: 0] opt,
  output reg [width : 0] out,
  output reg zero
  );
  
  always @ (*)
  begin
    case (opt)
      3'b000: out = a;
      3'b001: out = b - a;
      3'b010: out = a + b;
      3'b011: out = a & b;
      3'b100: out = a ^ b;
      3'b101: out = b;
      3'b110: out = a;
      3'b111: out = a;
      default: begin
        out = 1'b0;
      end
    endcase
end

always @ (*)
begin
if (a == 0)
zero = 1'b1;
else
zero = 1'b0;
end
   
endmodule

Labs/Lab_2/ALU_TB.v
module ALU_TB;
  reg  [7: 0] a, b;
  reg  [2: 0] opt;
  wire [8: 0] out;
  wire        zero;
  
  initial
  begin
    $dumpfile("ALU.vcd");
    $dumpvars;
    
    $display ("Test Case 1");
    
    a = 8'b01000010;
    b = 8'b10000110;
    opt = 000;
    
    #1
    
    if(out == 9'b001000010 && zero == 0)
      $display ("Test case 1 succeeded");
    else 
      begin
        $display ("Test case 1 failed");
      end
     $display ("Test Case 2");
    
    a = 8'b01000010;
    b = 8'b10000110;
    opt = 001;
    
    #1
    
    if(out == 9'b000000100 && zero == 0)
      $display ("Test case 2 succeeded");
    else 
      begin
        $display ("Test case 2 failed");
      end 
      
    $display ("Test Case 3");
    
    a = 8'b01000010;
    b = 8'b10000110;
    opt = 010;
    
    #1
    
    if(out == 9'b011001000 && zero == 0)
      $display ("Test case 3 succeeded");
    else 
      begin
        $display ("Test case 3 failed");
      end
      
    $display ("Test Case 4");
    
    a = 8'b01000010;
    b = 8'b10000110;
    opt = 011;
    
    #1
    
    if(out == 9'b000000010 && zero == 0)
      $display ("Test case 4 succeeded");
    else 
      begin
        $display ("Test case 4 failed");
      end

    $display ("Test Case 5");
    
    a = 8'b01000010;
    b = 8'b10000110;
    opt = 100;
    
    #1
    
    if(out == 9'b011000100 && zero == 0)
      $display ("Test case 5 succeeded");
    else 
      begin
        $display ("Test case 5 failed");
      end

    $display ("Test Case 6");
    
    a = 8'b01000010;
    b = 8'b10000110;
    opt = 101;
    
    #1
    
    if(out == 9'b010000110 && zero == 0)
      $display ("Test case 6 succeeded");
    else 
      begin
        $display ("Test case 6 failed");
      end

    $display ("Test Case 7");
    
    a = 8'b01000010;
    b = 8'b10000110;
    opt = 110;
    
    #1
    
    if(out == 9'b001000010 && zero == 0)
      $display ("Test case 7 succeeded");
    else 
      begin
        $display ("Test case 7 failed");
      end
      
    $display ("Test Case 8");
    
    a = 8'b01000010;
    b = 8'b10000110;
    opt = 111;
    
    #1
    
    if(out == 9'b01000010 && zero == 0)
      $display ("Test case 8 succeeded");
    else 
      begin
        $display ("Test case 8 failed");
      end

    $display ("Test Case 9");
    
    a = 8'b00000000;
    b = 8'b10000110;
    opt = 111;
    
    #1
    
    if(out == 9'b000000000 && zero == 1)
      $display ("Test case 9 succeeded");
    else 
      begin
        $display ("Test case 9 failed");
      end
    end    
 ALU DUT0 (
 .a(a),
 .b(b),
 .opt(opt),
 .out(out),
 .zero(zero)
 );
 
 endmodule

Labs/Lab_2/ALU.vcd
$date
	Wed Aug 26 23:58:40 2026
$end
$version
	ModelSim Version 10.1d
$end
$timescale
	1ps
$end
$scope module ALU_TB $end
$var reg 8 ! a [7:0] $end
$var reg 8 " b [7:0] $end
$var reg 3 # opt [2:0] $end
$var wire 1 $ out [8] $end
$var wire 1 % out [7] $end
$var wire 1 & out [6] $end
$var wire 1 ' out [5] $end
$var wire 1 ( out [4] $end
$var wire 1 ) out [3] $end
$var wire 1 * out [2] $end
$var wire 1 + out [1] $end
$var wire 1 , out [0] $end
$var wire 1 - zero $end
$scope module DUT0 $end
$var parameter 32 . width $end
$var wire 1 / a [7] $end
$var wire 1 0 a [6] $end
$var wire 1 1 a [5] $end
$var wire 1 2 a [4] $end
$var wire 1 3 a [3] $end
$var wire 1 4 a [2] $end
$var wire 1 5 a [1] $end
$var wire 1 6 a [0] $end
$var wire 1 7 b [7] $end
$var wire 1 8 b [6] $end
$var wire 1 9 b [5] $end
$var wire 1 : b [4] $end
$var wire 1 ; b [3] $end
$var wire 1 < b [2] $end
$var wire 1 = b [1] $end
$var wire 1 > b [0] $end
$var wire 1 ? opt [2] $end
$var wire 1 @ opt [1] $end
$var wire 1 A opt [0] $end
$var reg 9 B out [8:0] $end
$var reg 1 C zero $end
$upscope $end
$upscope $end
$enddefinitions $end
#0
$dumpvars
b1000010 !
b10000110 "
b0 #
b1000010 B
0C
b1000 .
0,
1+
0*
0)
0(
0'
1&
0%
0$
0-
0A
0@
0?
0>
1=
1<
0;
0:
09
08
17
06
15
04
03
02
01
10
0/
$end
#1
b1 #
1A
b1000100 B
0+
1*
#2
b10 #
0A
1@
b11001000 B
0*
1)
1%
#3
b11 #
1A
b10 B
1+
0)
0&
0%
#4
b100 #
0A
0@
1?
b11000100 B
0+
1*
1&
1%
#5
b101 #
1A
b10000110 B
1+
0&
#6
b110 #
0A
1@
b1000010 B
0*
1&
0%
#7
b111 #
1A
#8
b0 !
05
00
b0 B
1C
0+
0&
1-
